cdk_eks_container_insight/__init__.py
cdk_eks_container_insight/py.typed
cdk_eks_container_insight/_jsii/__init__.py
cdk_eks_container_insight/_jsii/cdk-eks-container-insight@0.0.15.jsii.tgz
cdk_eks_container_insight-0.0.15.dist-info/LICENSE
cdk_eks_container_insight-0.0.15.dist-info/METADATA
cdk_eks_container_insight-0.0.15.dist-info/NOTICE
cdk_eks_container_insight-0.0.15.dist-info/WHEEL
cdk_eks_container_insight-0.0.15.dist-info/top_level.txt
cdk_eks_container_insight-0.0.15.dist-info/RECORD
